{
  "quotes": [
    {
      "id": 2,
      "quote": "There are no secrets to success. It is the result of preparation, hard work, and learning from failure.",
      "likes": 20,
      "author": "Collin Powell"
    },
    {
      "id": 3,
      "quote": "Tell me and I forget, teach me and I remember, involve me and I learn.",
      "likes": 10,
      "author": "Benjamin Franklin"
    },
    {
      "id": 4,
      "quote": "Our greatest glory is not in never falling, but in rising everytime we fall.",
      "likes": 9,
      "author": "Confucius"
    },
    {
      "id": 5,
      "quote": "Success is not final, failure is not fatal: it is the courage to continue that counts.",
      "likes": 7,
      "author": "Winston Churchhill"
    },
    {
      "id": 6,
      "quote": "Perseverance is the hard work you do after you get tired of doing the hard work you already did.",
      "likes": 4,
      "author": "Newt Gingrich"
    },
    {
      "quote": "I RULE!!!!!",
      "author": "MC SAID THIS",
      "likes": 10,
      "id": 7
    }
  ]
}